LICENSE
README.md
setup.py
gamelibgames/__init__.py
gamelibgames/gamelib.py
gamelibgames/main.py
gamelibgames/menu.py
gamelibgames.egg-info/PKG-INFO
gamelibgames.egg-info/SOURCES.txt
gamelibgames.egg-info/dependency_links.txt
gamelibgames.egg-info/top_level.txt
gamelibgames/minesweeper/__init__.py
gamelibgames/minesweeper/color_profiles.txt
gamelibgames/minesweeper/figures.txt
gamelibgames/minesweeper/minefiles.py
gamelibgames/minesweeper/minegraphics.py
gamelibgames/minesweeper/minepaths.py
gamelibgames/minesweeper/minesweeper.py
gamelibgames/minesweeper/img/__init__.py
gamelibgames/minesweeper/img/demo/__init__.py
gamelibgames/minesweeper/img/demo/mines_go_kaboom.gif
gamelibgames/minesweeper/img/demo/playing.gif
gamelibgames/minesweeper/img/demo/resizing_and_winning.gif
gamelibgames/minesweeper/img/icon/__init__.py
gamelibgames/minesweeper/img/icon/minesweeper_logo.gif
gamelibgames/minesweeper/img/references/Nlgs Symbol_ref.png
gamelibgames/minesweeper/img/references/__init__.py
gamelibgames/minesweeper/img/references/sprite_references_1.png
gamelibgames/minesweeper/img/references/sprite_references_2.png
gamelibgames/minesweeper/img/references/sprite_references_3.png
gamelibgames/minesweeper/sfx/__init__.py
gamelibgames/minesweeper/sfx/boom.wav
gamelibgames/minesweeper/sfx/button_dn.wav
gamelibgames/minesweeper/sfx/button_up.wav
gamelibgames/minesweeper/sfx/marked.wav
gamelibgames/minesweeper/sfx/new_game.wav
gamelibgames/minesweeper/sfx/popup.wav
gamelibgames/minesweeper/sfx/uncovered_0.wav
gamelibgames/minesweeper/sfx/uncovered_1.wav
gamelibgames/minesweeper/sfx/uncovered_2.wav
gamelibgames/minesweeper/sfx/uncovered_3.wav
gamelibgames/minesweeper/sfx/uncovered_4.wav
gamelibgames/minesweeper/sfx/uncovered_5.wav
gamelibgames/minesweeper/sfx/uncovered_6.wav
gamelibgames/minesweeper/sfx/uncovered_7.wav
gamelibgames/minesweeper/sfx/uncovered_8.wav
gamelibgames/minesweeper/sfx/victory.wav
gamelibgames/picross/__init__.py
gamelibgames/picross/color_profiles.txt
gamelibgames/picross/picross.py
gamelibgames/picross/pifiles.py
gamelibgames/picross/pigraphics.py
gamelibgames/picross/pipaths.py
