Metadata-Version: 2.1
Name: gamelibgames
Version: 1.1.4
Summary: A collection of minigames made with Gamelib.
Home-page: https://github.com/NLGS2907/gamelib_games
Author: NLGS
Author-email: flighterman@fi.uba.ar
License: MIT
Keywords: GAMELIB,MINIGAMES
Platform: UNKNOWN
Classifier: Development Status :: 5 - Production/Stable
Classifier: License :: OSI Approved :: MIT License
Classifier: Programming Language :: Python :: 3.10
License-File: LICENSE
